encoo/__init__.py
encoo/config.py
encoo/eml.py
encoo/logger.py
encoo/util.py
encoo-2023.6.8.dist-info/METADATA
encoo-2023.6.8.dist-info/WHEEL
encoo-2023.6.8.dist-info/top_level.txt
encoo-2023.6.8.dist-info/RECORD
