Metadata-Version: 2.1
Name: encoo
Version: 2023.6.8
Requires-Dist: xlwt (>=1.3.0)
Requires-Dist: xlrd (==1.2.0)
Requires-Dist: configparser (>=5.3.0)
Requires-Dist: mail-parser (>=3.15.0)
Requires-Dist: extract-msg (>=0.40.0)
